tempavg.py
tempavg-1.0.3.dist-info/METADATA
tempavg-1.0.3.dist-info/WHEEL
tempavg-1.0.3.dist-info/entry_points.txt
tempavg-1.0.3.dist-info/top_level.txt
tempavg-1.0.3.dist-info/RECORD
