Metadata-Version: 2.1
Name: tempavg
Version: 1.0.3
Summary: Changes in average temperature in Japanese cities
Home-page: https://github.com/Shimpo-Yumiko/
Author: yumiko shimpo
Author-email: yumikoshippo@gmail.com
License: UNKNOWN
Project-URL: Bug Tracker, https://github.com/Shimpo-Yumiko/
Platform: UNKNOWN
Classifier: Programming Language :: Python :: 3
Requires-Python: >=3.7
